primrea/__init__.py
primrea/core.py
primrea/kh_table_gen/__init__.py
primrea/kh_table_gen/entry_based.py
primrea/kh_table_gen/pjdb.py
primrea/tests/__init__.py
primrea-0.1.0.dist-info/METADATA
primrea-0.1.0.dist-info/WHEEL
primrea-0.1.0.dist-info/top_level.txt
primrea-0.1.0.dist-info/RECORD
