Metadata-Version: 2.1
Name: primrea
Version: 0.1.0
Summary: Access to PRIMRE knowledge hub metadata and content.
Author: Dominick DeCanio
Author-email: dominick.c.decanio@pnnl.gov
License: BSD 3
Requires-Dist: requests
Requires-Dist: pandas
